LICENSE
MANIFEST.in
README.rst
deasciiify.py
setup.py
deasciiify.egg-info/PKG-INFO
deasciiify.egg-info/SOURCES.txt
deasciiify.egg-info/dependency_links.txt
deasciiify.egg-info/requires.txt
deasciiify.egg-info/top_level.txt