Metadata-Version: 2.1
Name: deasciiify
Version: 0.0.2
Summary: Translate ASCII text into readable non-ASCII text
Home-page: https://github.com/jnrbsn/deasciiify
Author: Jonathan Robson
Author-email: jnrbsn@gmail.com
License: MIT
Platform: UNKNOWN
Classifier: Development Status :: 4 - Beta
Classifier: License :: OSI Approved :: MIT License
Classifier: Programming Language :: Python :: 2.7
Provides-Extra: test
